README
ez_setup.py
marcup.py
setup.py
bin/marcup
marcup.egg-info/PKG-INFO
marcup.egg-info/SOURCES.txt
marcup.egg-info/dependency_links.txt
marcup.egg-info/requires.txt
marcup.egg-info/top_level.txt