Metadata-Version: 1.0
Name: marcup
Version: 0.2
Summary: manage create/update/deletes marc feeds
Home-page: http://cheeseshop.python.org/pypi/marcup
Author: Ed Summers
Author-email: ehs@pobox.com
License: http://creativecommons.org/licenses/publicdomain/
Platform: UNKNOWN
Classifier: Intended Audience :: Developers
Classifier: Intended Audience :: Information Technology
Classifier: License :: Public Domain 
Classifier: Programming Language :: Python
Classifier: Topic :: Text Processing :: General
